[
  {
    "x": 0,
    "q_x": 0.01398
  },
  {
    "x": 1,
    "q_x": 0.00097
  },
  {
    "x": 2,
    "q_x": 0.00065
  },
  {
    "x": 3,
    "q_x": 0.000529
  },
  {
    "x": 4,
    "q_x": 0.000379
  },
  {
    "x": 5,
    "q_x": 0.000328
  },
  {
    "x": 6,
    "q_x": 0.000289
  },
  {
    "x": 7,
    "q_x": 0.000283
  },
  {
    "x": 8,
    "q_x": 0.000262
  },
  {
    "x": 9,
    "q_x": 0.000259
  },
  {
    "x": 10,
    "q_x": 0.000215
  },
  {
    "x": 11,
    "q_x": 0.000244
  },
  {
    "x": 12,
    "q_x": 0.000271
  },
  {
    "x": 13,
    "q_x": 0.000372
  },
  {
    "x": 14,
    "q_x": 0.000517
  },
  {
    "x": 15,
    "q_x": 0.00071
  },
  {
    "x": 16,
    "q_x": 0.000894
  },
  {
    "x": 17,
    "q_x": 0.001064
  },
  {
    "x": 18,
    "q_x": 0.001205
  },
  {
    "x": 19,
    "q_x": 0.00128
  },
  {
    "x": 20,
    "q_x": 0.001368
  },
  {
    "x": 21,
    "q_x": 0.001446
  },
  {
    "x": 22,
    "q_x": 0.001428
  },
  {
    "x": 23,
    "q_x": 0.001439
  },
  {
    "x": 24,
    "q_x": 0.001417
  },
  {
    "x": 25,
    "q_x": 0.001468
  },
  {
    "x": 26,
    "q_x": 0.001505
  },
  {
    "x": 27,
    "q_x": 0.001463
  },
  {
    "x": 28,
    "q_x": 0.001444
  },
  {
    "x": 29,
    "q_x": 0.001419
  },
  {
    "x": 30,
    "q_x": 0.001413
  },
  {
    "x": 31,
    "q_x": 0.001456
  },
  {
    "x": 32,
    "q_x": 0.00149
  },
  {
    "x": 33,
    "q_x": 0.001562
  },
  {
    "x": 34,
    "q_x": 0.001668
  },
  {
    "x": 35,
    "q_x": 0.001841
  },
  {
    "x": 36,
    "q_x": 0.002088
  },
  {
    "x": 37,
    "q_x": 0.002228
  },
  {
    "x": 38,
    "q_x": 0.002306
  },
  {
    "x": 39,
    "q_x": 0.002468
  },
  {
    "x": 40,
    "q_x": 0.003257
  },
  {
    "x": 41,
    "q_x": 0.003965
  },
  {
    "x": 42,
    "q_x": 0.003642
  },
  {
    "x": 43,
    "q_x": 0.00362
  },
  {
    "x": 44,
    "q_x": 0.002934
  },
  {
    "x": 45,
    "q_x": 0.003115
  },
  {
    "x": 46,
    "q_x": 0.003285
  },
  {
    "x": 47,
    "q_x": 0.003472
  },
  {
    "x": 48,
    "q_x": 0.003691
  },
  {
    "x": 49,
    "q_x": 0.003954
  },
  {
    "x": 50,
    "q_x": 0.004266
  },
  {
    "x": 51,
    "q_x": 0.004625
  },
  {
    "x": 52,
    "q_x": 0.00503
  },
  {
    "x": 53,
    "q_x": 0.005483
  },
  {
    "x": 54,
    "q_x": 0.005981
  },
  {
    "x": 55,
    "q_x": 0.006502
  },
  {
    "x": 56,
    "q_x": 0.007036
  },
  {
    "x": 57,
    "q_x": 0.007587
  },
  {
    "x": 58,
    "q_x": 0.008157
  },
  {
    "x": 59,
    "q_x": 0.008757
  },
  {
    "x": 60,
    "q_x": 0.009392
  },
  {
    "x": 61,
    "q_x": 0.010067
  },
  {
    "x": 62,
    "q_x": 0.010764
  },
  {
    "x": 63,
    "q_x": 0.011476
  },
  {
    "x": 64,
    "q_x": 0.012229
  },
  {
    "x": 65,
    "q_x": 0.013039
  },
  {
    "x": 66,
    "q_x": 0.013764
  },
  {
    "x": 67,
    "q_x": 0.014416
  },
  {
    "x": 68,
    "q_x": 0.015086
  },
  {
    "x": 69,
    "q_x": 0.015884
  },
  {
    "x": 70,
    "q_x": 0.016895
  },
  {
    "x": 71,
    "q_x": 0.018173
  },
  {
    "x": 72,
    "q_x": 0.019737
  },
  {
    "x": 73,
    "q_x": 0.021555
  },
  {
    "x": 74,
    "q_x": 0.023542
  },
  {
    "x": 75,
    "q_x": 0.025681
  },
  {
    "x": 76,
    "q_x": 0.028002
  },
  {
    "x": 77,
    "q_x": 0.030564
  },
  {
    "x": 78,
    "q_x": 0.033407
  },
  {
    "x": 79,
    "q_x": 0.036574
  },
  {
    "x": 80,
    "q_x": 0.040099
  },
  {
    "x": 81,
    "q_x": 0.044067
  },
  {
    "x": 82,
    "q_x": 0.048662
  },
  {
    "x": 83,
    "q_x": 0.054253
  },
  {
    "x": 84,
    "q_x": 0.061343
  },
  {
    "x": 85,
    "q_x": 0.070106
  },
  {
    "x": 86,
    "q_x": 0.079073
  },
  {
    "x": 87,
    "q_x": 0.088241
  },
  {
    "x": 88,
    "q_x": 0.097889
  },
  {
    "x": 89,
    "q_x": 0.108221
  },
  {
    "x": 90,
    "q_x": 0.119366
  },
  {
    "x": 91,
    "q_x": 0.131437
  },
  {
    "x": 92,
    "q_x": 0.144571
  },
  {
    "x": 93,
    "q_x": 0.158869
  },
  {
    "x": 94,
    "q_x": 0.174341
  },
  {
    "x": 95,
    "q_x": 0.190857
  },
  {
    "x": 96,
    "q_x": 0.207908
  },
  {
    "x": 97,
    "q_x": 0.224624
  },
  {
    "x": 98,
    "q_x": 0.240103
  },
  {
    "x": 99,
    "q_x": 0.254257
  },
  {
    "x": 100,
    "q_x": 0.268519
  },
  {
    "x": 101,
    "q_x": 0.282813
  },
  {
    "x": 102,
    "q_x": 0.297057
  },
  {
    "x": 103,
    "q_x": 0.311168
  },
  {
    "x": 104,
    "q_x": 0.325056
  },
  {
    "x": 105,
    "q_x": 0.339573
  },
  {
    "x": 106,
    "q_x": 0.354747
  },
  {
    "x": 107,
    "q_x": 0.370608
  },
  {
    "x": 108,
    "q_x": 0.387189
  },
  {
    "x": 109,
    "q_x": 0.404522
  },
  {
    "x": 110,
    "q_x": 0.422641
  },
  {
    "x": 111,
    "q_x": 0.441584
  },
  {
    "x": 112,
    "q_x": 0.461387
  },
  {
    "x": 113,
    "q_x": 0.48209
  },
  {
    "x": 114,
    "q_x": 0.503735
  },
  {
    "x": 115,
    "q_x": 0.526366
  },
  {
    "x": 116,
    "q_x": 0.550026
  },
  {
    "x": 117,
    "q_x": 0.574765
  },
  {
    "x": 118,
    "q_x": 0.60063
  },
  {
    "x": 119,
    "q_x": 0.627676
  }
]