[
  {
    "x": 0,
    "q_x": 0.030202
  },
  {
    "x": 1,
    "q_x": 0.001822
  },
  {
    "x": 2,
    "q_x": 0.001163
  },
  {
    "x": 3,
    "q_x": 0.000844
  },
  {
    "x": 4,
    "q_x": 0.000651
  },
  {
    "x": 5,
    "q_x": 0.00061
  },
  {
    "x": 6,
    "q_x": 0.00056
  },
  {
    "x": 7,
    "q_x": 0.000505
  },
  {
    "x": 8,
    "q_x": 0.000467
  },
  {
    "x": 9,
    "q_x": 0.0004
  },
  {
    "x": 10,
    "q_x": 0.000416
  },
  {
    "x": 11,
    "q_x": 0.000418
  },
  {
    "x": 12,
    "q_x": 0.000464
  },
  {
    "x": 13,
    "q_x": 0.00054
  },
  {
    "x": 14,
    "q_x": 0.000728
  },
  {
    "x": 15,
    "q_x": 0.00099
  },
  {
    "x": 16,
    "q_x": 0.001241
  },
  {
    "x": 17,
    "q_x": 0.001485
  },
  {
    "x": 18,
    "q_x": 0.001675
  },
  {
    "x": 19,
    "q_x": 0.001905
  },
  {
    "x": 20,
    "q_x": 0.001984
  },
  {
    "x": 21,
    "q_x": 0.002015
  },
  {
    "x": 22,
    "q_x": 0.002058
  },
  {
    "x": 23,
    "q_x": 0.001889
  },
  {
    "x": 24,
    "q_x": 0.001748
  },
  {
    "x": 25,
    "q_x": 0.001632
  },
  {
    "x": 26,
    "q_x": 0.001646
  },
  {
    "x": 27,
    "q_x": 0.001673
  },
  {
    "x": 28,
    "q_x": 0.001849
  },
  {
    "x": 29,
    "q_x": 0.001869
  },
  {
    "x": 30,
    "q_x": 0.002022
  },
  {
    "x": 31,
    "q_x": 0.002132
  },
  {
    "x": 32,
    "q_x": 0.002232
  },
  {
    "x": 33,
    "q_x": 0.002318
  },
  {
    "x": 34,
    "q_x": 0.002428
  },
  {
    "x": 35,
    "q_x": 0.002596
  },
  {
    "x": 36,
    "q_x": 0.002741
  },
  {
    "x": 37,
    "q_x": 0.002894
  },
  {
    "x": 38,
    "q_x": 0.002696
  },
  {
    "x": 39,
    "q_x": 0.002485
  },
  {
    "x": 40,
    "q_x": 0.002576
  },
  {
    "x": 41,
    "q_x": 0.00278
  },
  {
    "x": 42,
    "q_x": 0.003026
  },
  {
    "x": 43,
    "q_x": 0.003282
  },
  {
    "x": 44,
    "q_x": 0.003576
  },
  {
    "x": 45,
    "q_x": 0.003874
  },
  {
    "x": 46,
    "q_x": 0.004094
  },
  {
    "x": 47,
    "q_x": 0.004408
  },
  {
    "x": 48,
    "q_x": 0.004764
  },
  {
    "x": 49,
    "q_x": 0.005005
  },
  {
    "x": 50,
    "q_x": 0.00541
  },
  {
    "x": 51,
    "q_x": 0.005838
  },
  {
    "x": 52,
    "q_x": 0.006099
  },
  {
    "x": 53,
    "q_x": 0.006648
  },
  {
    "x": 54,
    "q_x": 0.007133
  },
  {
    "x": 55,
    "q_x": 0.007722
  },
  {
    "x": 56,
    "q_x": 0.008397
  },
  {
    "x": 57,
    "q_x": 0.009049
  },
  {
    "x": 58,
    "q_x": 0.009768
  },
  {
    "x": 59,
    "q_x": 0.010468
  },
  {
    "x": 60,
    "q_x": 0.011201
  },
  {
    "x": 61,
    "q_x": 0.011983
  },
  {
    "x": 62,
    "q_x": 0.015258
  },
  {
    "x": 63,
    "q_x": 0.017537
  },
  {
    "x": 64,
    "q_x": 0.016737
  },
  {
    "x": 65,
    "q_x": 0.016447
  },
  {
    "x": 66,
    "q_x": 0.017008
  },
  {
    "x": 67,
    "q_x": 0.017485
  },
  {
    "x": 68,
    "q_x": 0.018335
  },
  {
    "x": 69,
    "q_x": 0.019327
  },
  {
    "x": 70,
    "q_x": 0.020552
  },
  {
    "x": 71,
    "q_x": 0.022078
  },
  {
    "x": 72,
    "q_x": 0.02393
  },
  {
    "x": 73,
    "q_x": 0.026071
  },
  {
    "x": 74,
    "q_x": 0.028402
  },
  {
    "x": 75,
    "q_x": 0.030904
  },
  {
    "x": 76,
    "q_x": 0.033618
  },
  {
    "x": 77,
    "q_x": 0.036619
  },
  {
    "x": 78,
    "q_x": 0.039954
  },
  {
    "x": 79,
    "q_x": 0.043679
  },
  {
    "x": 80,
    "q_x": 0.047834
  },
  {
    "x": 81,
    "q_x": 0.052504
  },
  {
    "x": 82,
    "q_x": 0.057835
  },
  {
    "x": 83,
    "q_x": 0.064087
  },
  {
    "x": 84,
    "q_x": 0.071608
  },
  {
    "x": 85,
    "q_x": 0.080567
  },
  {
    "x": 86,
    "q_x": 0.090121
  },
  {
    "x": 87,
    "q_x": 0.10027
  },
  {
    "x": 88,
    "q_x": 0.111153
  },
  {
    "x": 89,
    "q_x": 0.122868
  },
  {
    "x": 90,
    "q_x": 0.135495
  },
  {
    "x": 91,
    "q_x": 0.149142
  },
  {
    "x": 92,
    "q_x": 0.163968
  },
  {
    "x": 93,
    "q_x": 0.180101
  },
  {
    "x": 94,
    "q_x": 0.197559
  },
  {
    "x": 95,
    "q_x": 0.216185
  },
  {
    "x": 96,
    "q_x": 0.235375
  },
  {
    "x": 97,
    "q_x": 0.254135
  },
  {
    "x": 98,
    "q_x": 0.271451
  },
  {
    "x": 99,
    "q_x": 0.287241
  },
  {
    "x": 100,
    "q_x": 0.303141
  },
  {
    "x": 101,
    "q_x": 0.319066
  },
  {
    "x": 102,
    "q_x": 0.334924
  },
  {
    "x": 103,
    "q_x": 0.350622
  },
  {
    "x": 104,
    "q_x": 0.36606
  },
  {
    "x": 105,
    "q_x": 0.382188
  },
  {
    "x": 106,
    "q_x": 0.399036
  },
  {
    "x": 107,
    "q_x": 0.416638
  },
  {
    "x": 108,
    "q_x": 0.435029
  },
  {
    "x": 109,
    "q_x": 0.454243
  },
  {
    "x": 110,
    "q_x": 0.474318
  },
  {
    "x": 111,
    "q_x": 0.495293
  },
  {
    "x": 112,
    "q_x": 0.51721
  },
  {
    "x": 113,
    "q_x": 0.54011
  },
  {
    "x": 114,
    "q_x": 0.56404
  },
  {
    "x": 115,
    "q_x": 0.589045
  },
  {
    "x": 116,
    "q_x": 0.615174
  },
  {
    "x": 117,
    "q_x": 0.64248
  },
  {
    "x": 118,
    "q_x": 0.671015
  },
  {
    "x": 119,
    "q_x": 0.700836
  }
]