[
  {
    "x": 0,
    "q_x": 0.002016
  },
  {
    "x": 1,
    "q_x": 0.000168
  },
  {
    "x": 2,
    "q_x": 9.9e-05
  },
  {
    "x": 3,
    "q_x": 8e-05
  },
  {
    "x": 4,
    "q_x": 6.5e-05
  },
  {
    "x": 5,
    "q_x": 5.4e-05
  },
  {
    "x": 6,
    "q_x": 4.8e-05
  },
  {
    "x": 7,
    "q_x": 4.3e-05
  },
  {
    "x": 8,
    "q_x": 4.1e-05
  },
  {
    "x": 9,
    "q_x": 4e-05
  },
  {
    "x": 10,
    "q_x": 4.1e-05
  },
  {
    "x": 11,
    "q_x": 4.4e-05
  },
  {
    "x": 12,
    "q_x": 5.4e-05
  },
  {
    "x": 13,
    "q_x": 7.6e-05
  },
  {
    "x": 14,
    "q_x": 0.000119
  },
  {
    "x": 15,
    "q_x": 0.000187
  },
  {
    "x": 16,
    "q_x": 0.00027
  },
  {
    "x": 17,
    "q_x": 0.000362
  },
  {
    "x": 18,
    "q_x": 0.000456
  },
  {
    "x": 19,
    "q_x": 0.000544
  },
  {
    "x": 20,
    "q_x": 0.000621
  },
  {
    "x": 21,
    "q_x": 0.000684
  },
  {
    "x": 22,
    "q_x": 0.000733
  },
  {
    "x": 23,
    "q_x": 0.000773
  },
  {
    "x": 24,
    "q_x": 0.000813
  },
  {
    "x": 25,
    "q_x": 0.000854
  },
  {
    "x": 26,
    "q_x": 0.000895
  },
  {
    "x": 27,
    "q_x": 0.000931
  },
  {
    "x": 28,
    "q_x": 0.000961
  },
  {
    "x": 29,
    "q_x": 0.000984
  },
  {
    "x": 30,
    "q_x": 0.000998
  },
  {
    "x": 31,
    "q_x": 0.001008
  },
  {
    "x": 32,
    "q_x": 0.001019
  },
  {
    "x": 33,
    "q_x": 0.001036
  },
  {
    "x": 34,
    "q_x": 0.001058
  },
  {
    "x": 35,
    "q_x": 0.001079
  },
  {
    "x": 36,
    "q_x": 0.001099
  },
  {
    "x": 37,
    "q_x": 0.001117
  },
  {
    "x": 38,
    "q_x": 0.001131
  },
  {
    "x": 39,
    "q_x": 0.001138
  },
  {
    "x": 40,
    "q_x": 0.001137
  },
  {
    "x": 41,
    "q_x": 0.001132
  },
  {
    "x": 42,
    "q_x": 0.00113
  },
  {
    "x": 43,
    "q_x": 0.001141
  },
  {
    "x": 44,
    "q_x": 0.001165
  },
  {
    "x": 45,
    "q_x": 0.001201
  },
  {
    "x": 46,
    "q_x": 0.001246
  },
  {
    "x": 47,
    "q_x": 0.001304
  },
  {
    "x": 48,
    "q_x": 0.001389
  },
  {
    "x": 49,
    "q_x": 0.001519
  },
  {
    "x": 50,
    "q_x": 0.001696
  },
  {
    "x": 51,
    "q_x": 0.001862
  },
  {
    "x": 52,
    "q_x": 0.002018
  },
  {
    "x": 53,
    "q_x": 0.002178
  },
  {
    "x": 54,
    "q_x": 0.002349
  },
  {
    "x": 55,
    "q_x": 0.002526
  },
  {
    "x": 56,
    "q_x": 0.002705
  },
  {
    "x": 57,
    "q_x": 0.002885
  },
  {
    "x": 58,
    "q_x": 0.003066
  },
  {
    "x": 59,
    "q_x": 0.003248
  },
  {
    "x": 60,
    "q_x": 0.003434
  },
  {
    "x": 61,
    "q_x": 0.003633
  },
  {
    "x": 62,
    "q_x": 0.003877
  },
  {
    "x": 63,
    "q_x": 0.00425
  },
  {
    "x": 64,
    "q_x": 0.004879
  },
  {
    "x": 65,
    "q_x": 0.005791
  },
  {
    "x": 66,
    "q_x": 0.006476
  },
  {
    "x": 67,
    "q_x": 0.006933
  },
  {
    "x": 68,
    "q_x": 0.007304
  },
  {
    "x": 69,
    "q_x": 0.007719
  },
  {
    "x": 70,
    "q_x": 0.008254
  },
  {
    "x": 71,
    "q_x": 0.008945
  },
  {
    "x": 72,
    "q_x": 0.009806
  },
  {
    "x": 73,
    "q_x": 0.010822
  },
  {
    "x": 74,
    "q_x": 0.011954
  },
  {
    "x": 75,
    "q_x": 0.01319
  },
  {
    "x": 76,
    "q_x": 0.01454
  },
  {
    "x": 77,
    "q_x": 0.016032
  },
  {
    "x": 78,
    "q_x": 0.017687
  },
  {
    "x": 79,
    "q_x": 0.019529
  },
  {
    "x": 80,
    "q_x": 0.02158
  },
  {
    "x": 81,
    "q_x": 0.02391
  },
  {
    "x": 82,
    "q_x": 0.026719
  },
  {
    "x": 83,
    "q_x": 0.030439
  },
  {
    "x": 84,
    "q_x": 0.035667
  },
  {
    "x": 85,
    "q_x": 0.042545
  },
  {
    "x": 86,
    "q_x": 0.049094
  },
  {
    "x": 87,
    "q_x": 0.055308
  },
  {
    "x": 88,
    "q_x": 0.061597
  },
  {
    "x": 89,
    "q_x": 0.06827
  },
  {
    "x": 90,
    "q_x": 0.075504
  },
  {
    "x": 91,
    "q_x": 0.083411
  },
  {
    "x": 92,
    "q_x": 0.092071
  },
  {
    "x": 93,
    "q_x": 0.101513
  },
  {
    "x": 94,
    "q_x": 0.111712
  },
  {
    "x": 95,
    "q_x": 0.122585
  },
  {
    "x": 96,
    "q_x": 0.133852
  },
  {
    "x": 97,
    "q_x": 0.144983
  },
  {
    "x": 98,
    "q_x": 0.155386
  },
  {
    "x": 99,
    "q_x": 0.164991
  },
  {
    "x": 100,
    "q_x": 0.174699
  },
  {
    "x": 101,
    "q_x": 0.184456
  },
  {
    "x": 102,
    "q_x": 0.194206
  },
  {
    "x": 103,
    "q_x": 0.20389
  },
  {
    "x": 104,
    "q_x": 0.213444
  },
  {
    "x": 105,
    "q_x": 0.223448
  },
  {
    "x": 106,
    "q_x": 0.233925
  },
  {
    "x": 107,
    "q_x": 0.244896
  },
  {
    "x": 108,
    "q_x": 0.256385
  },
  {
    "x": 109,
    "q_x": 0.268416
  },
  {
    "x": 110,
    "q_x": 0.281015
  },
  {
    "x": 111,
    "q_x": 0.294209
  },
  {
    "x": 112,
    "q_x": 0.308026
  },
  {
    "x": 113,
    "q_x": 0.322496
  },
  {
    "x": 114,
    "q_x": 0.33765
  },
  {
    "x": 115,
    "q_x": 0.35352
  },
  {
    "x": 116,
    "q_x": 0.37014
  },
  {
    "x": 117,
    "q_x": 0.387547
  },
  {
    "x": 118,
    "q_x": 0.405776
  },
  {
    "x": 119,
    "q_x": 0.424868
  }
]